trunner/VERSION.txt
trunner/__init__.py
trunner/base.py
trunner/dummy.py
trunner/tbase.py
trunner-1.0.4.dist-info/METADATA
trunner-1.0.4.dist-info/WHEEL
trunner-1.0.4.dist-info/top_level.txt
trunner-1.0.4.dist-info/RECORD
