Metadata-Version: 2.1
Name: trunner
Version: 1.0.4
Summary: runner于运行job的py package 封装
Home-page: https://github.com/tradingAI/runner/tree/master/python
Author: liuwen
Author-email: liuwen.w@qq.com
License: UNKNOWN
Platform: UNKNOWN
Classifier: Programming Language :: Python :: 3
Classifier: License :: OSI Approved :: MIT License
Classifier: Operating System :: OS Independent
Requires-Python: >=3
